deep_research/__init__.py
deep_research/prompts.py
deep_research/researcher.py
deep_researcher_sdk-0.1.1.dist-info/METADATA
deep_researcher_sdk-0.1.1.dist-info/WHEEL
deep_researcher_sdk-0.1.1.dist-info/licenses/LICENSE
deep_researcher_sdk-0.1.1.dist-info/RECORD
