Metadata-Version: 2.4
Name: deep-researcher-sdk
Version: 0.1.1
Summary: Python SDK for deep research using Gemini with search grounding
Project-URL: Repository, https://github.com/nouamanecodes/deep-research-sdk
License-Expression: MIT
License-File: LICENSE
Requires-Python: >=3.12
Requires-Dist: google-genai>=1.0.0
Requires-Dist: pydantic>=2.0.0
Provides-Extra: dev
Requires-Dist: pytest>=8.0.0; extra == 'dev'
